orchestrator/__init__.py
orchestrator/app.py
orchestrator/build_pipeline.py
orchestrator/orchestrator_runner.py
orchestrator/pipeline_builder.py
orchestrator/pipeline_orchestrator.py
orchestrator/py.typed
orchestrator/review_persistence.py
orchestrator/static/favicon.svg
orchestrator/static/orchestrator.css
orchestrator/static/orchestrator.html
orchestrator/static/orchestrator.js
orchestrator/static/review_common.js
orchestrator/static/review_identical.html
orchestrator/static/review_sequences.html
overlap_metrics/__init__.py
overlap_metrics/config.py
overlap_metrics/core.py
overlap_metrics/estimators.py
overlap_metrics/metrics.py
overlap_metrics/registry.py
overlap_metrics/utils.py
photo_compare/__init__.py
photo_compare/base.py
photo_compare/config.py
photo_compare/distance.py
photo_compare/feature_methods.py
photo_compare/file_hash.py
photo_compare/hash_methods.py
photo_compare/histogram_methods.py
photo_compare/pixel_methods.py
photo_compare/py.typed
photo_compare/structural_methods.py
photo_compare/types.py
photo_stack_finder-0.1.7.dist-info/licenses/LICENSE
scripts/orchestrate.py
utils/__init__.py
utils/base_pipeline_stage.py
utils/base_ports.py
utils/benchmark_utils.py
utils/channel.py
utils/comparison_gates.py
utils/compute_benchmarks.py
utils/compute_identical.py
utils/compute_indices.py
utils/compute_perceptual_hash.py
utils/compute_perceptual_match.py
utils/compute_sha_bins.py
utils/compute_template_similarity.py
utils/compute_templates.py
utils/compute_versions.py
utils/config.py
utils/data_io.py
utils/graph_context.py
utils/logger.py
utils/models.py
utils/photo_file.py
utils/pipeline_graph.py
utils/pipeline_stage.py
utils/plot_helpers.py
utils/ports.py
utils/progress.py
utils/py.typed
utils/report_builder.py
utils/review_types.py
utils/review_utils.py
utils/sequence.py
utils/sequence_clustering.py
utils/template.py
photo_stack_finder-0.1.7.dist-info/METADATA
photo_stack_finder-0.1.7.dist-info/WHEEL
photo_stack_finder-0.1.7.dist-info/entry_points.txt
photo_stack_finder-0.1.7.dist-info/top_level.txt
photo_stack_finder-0.1.7.dist-info/RECORD
