Metadata-Version: 2.4
Name: photo-stack-finder
Version: 0.1.7
Summary: Photo deduplication using perceptual hashing and sequence detection
Author: Geoff Barrett
Maintainer: Geoff Barrett
License: AGPL-3.0-or-later
Project-URL: Homepage, https://github.com/gbarrett28/photo_dedup
Project-URL: Repository, https://github.com/gbarrett28/photo_dedup
Project-URL: Issues, https://github.com/gbarrett28/photo_dedup/issues
Project-URL: Discussions, https://github.com/gbarrett28/photo_dedup/discussions
Keywords: photo,deduplication,perceptual-hashing,image-processing
Classifier: Development Status :: 4 - Beta
Classifier: Intended Audience :: End Users/Desktop
Classifier: License :: OSI Approved :: GNU Affero General Public License v3 or later (AGPLv3+)
Classifier: Programming Language :: Python :: 3
Classifier: Programming Language :: Python :: 3.11
Classifier: Programming Language :: Python :: 3.12
Classifier: Programming Language :: Python :: 3.13
Classifier: Topic :: Multimedia :: Graphics
Classifier: Topic :: Utilities
Requires-Python: >=3.11
License-File: LICENSE
Requires-Dist: numpy<2.5.0
Requires-Dist: pillow
Requires-Dist: pillow_heif
Requires-Dist: pandas
Requires-Dist: opencv-python-headless>=4.12.0
Requires-Dist: scikit-image
Requires-Dist: scipy
Requires-Dist: ImageHash
Requires-Dist: joblib>=1.3.0
Requires-Dist: imagesize
Requires-Dist: PyWavelets
Requires-Dist: tifffile
Requires-Dist: imageio
Requires-Dist: networkx
Requires-Dist: python-dateutil
Requires-Dist: pytz
Requires-Dist: tzdata
Requires-Dist: psutil
Requires-Dist: matplotlib>=3.10.0
Requires-Dist: scikit-learn>=1.7.0
Requires-Dist: fastapi
Requires-Dist: uvicorn[standard]
Requires-Dist: websockets
Provides-Extra: dev
Requires-Dist: ruff; extra == "dev"
Requires-Dist: mypy; extra == "dev"
Requires-Dist: pre-commit; extra == "dev"
Requires-Dist: autopep8; extra == "dev"
Requires-Dist: pytest; extra == "dev"
Requires-Dist: pytest-cov; extra == "dev"
Dynamic: license-file
